MANIFEST.in
README.txt
setup.py
c2/__init__.py
c2.patch.dateforlisting.egg-info/PKG-INFO
c2.patch.dateforlisting.egg-info/SOURCES.txt
c2.patch.dateforlisting.egg-info/dependency_links.txt
c2.patch.dateforlisting.egg-info/entry_points.txt
c2.patch.dateforlisting.egg-info/namespace_packages.txt
c2.patch.dateforlisting.egg-info/not-zip-safe
c2.patch.dateforlisting.egg-info/requires.txt
c2.patch.dateforlisting.egg-info/top_level.txt
c2/patch/__init__.py
c2/patch/dateforlisting/__init__.py
c2/patch/dateforlisting/configure.zcml
c2/patch/dateforlisting/monkey.py
c2/patch/dateforlisting/version.txt
c2/patch/dateforlisting/profiles/default/metadata.xml
c2/patch/dateforlisting/profiles/default/skins.xml
c2/patch/dateforlisting/skins/dateforlisting/getFolderContents.py
c2/patch/dateforlisting/tests/__init__.py
c2/patch/dateforlisting/tests/base.py
c2/patch/dateforlisting/tests/test_setup.py
docs/HISTORY.txt
docs/INSTALL.txt
docs/LICENSE.GPL
docs/LICENSE.txt